collective.behavior.richpreview-1.0a1-py2.7-nspkg.pth
collective/behavior/__init__.py
collective/behavior/__init__.pyc
collective/behavior/richpreview/__init__.py
collective/behavior/richpreview/__init__.pyc
collective/behavior/richpreview/behaviors.py
collective/behavior/richpreview/behaviors.pyc
collective/behavior/richpreview/behaviors.zcml
collective/behavior/richpreview/config.py
collective/behavior/richpreview/config.pyc
collective/behavior/richpreview/configure.zcml
collective/behavior/richpreview/interfaces.py
collective/behavior/richpreview/interfaces.pyc
collective/behavior/richpreview/profiles.zcml
collective/behavior/richpreview/setuphandlers.py
collective/behavior/richpreview/setuphandlers.pyc
collective/behavior/richpreview/testing.py
collective/behavior/richpreview/testing.pyc
collective/behavior/richpreview/Extensions/Install.py
collective/behavior/richpreview/Extensions/__init__.py
collective/behavior/richpreview/browser/__init__.py
collective/behavior/richpreview/browser/__init__.pyc
collective/behavior/richpreview/browser/configure.zcml
collective/behavior/richpreview/browser/controlpanel.py
collective/behavior/richpreview/browser/controlpanel.pyc
collective/behavior/richpreview/browser/richpreview.pt
collective/behavior/richpreview/browser/richpreview.py
collective/behavior/richpreview/browser/richpreview.pyc
collective/behavior/richpreview/browser/static/richpreview.css
collective/behavior/richpreview/browser/static/richpreview.css.map
collective/behavior/richpreview/browser/static/richpreview.js
collective/behavior/richpreview/browser/static/richpreview.js.map
collective/behavior/richpreview/browser/static/img/preview.png
collective/behavior/richpreview/locales/collective.behavior.richpreview.pot
collective/behavior/richpreview/locales/manual.pot
collective/behavior/richpreview/locales/plone.pot
collective/behavior/richpreview/locales/es/LC_MESSAGES/collective.behavior.richpreview.mo
collective.behavior.richpreview-1.0a1.dist-info/DESCRIPTION.rst
collective.behavior.richpreview-1.0a1.dist-info/METADATA
collective.behavior.richpreview-1.0a1.dist-info/RECORD
collective.behavior.richpreview-1.0a1.dist-info/WHEEL
collective.behavior.richpreview-1.0a1.dist-info/entry_points.txt
collective.behavior.richpreview-1.0a1.dist-info/metadata.json
collective.behavior.richpreview-1.0a1.dist-info/namespace_packages.txt
collective.behavior.richpreview-1.0a1.dist-info/top_level.txt
