Metadata-Version: 2.0
Name: collective.behavior.richpreview
Version: 1.0a1
Summary: A behavior for Dexterity-based content types to show previews on hover over hyperlinks in content area.
Home-page: https://github.com/collective/behavior.richpreview
Author: UNKNOWN
Author-email: UNKNOWN
License: UNKNOWN
Keywords: plone rich link preview
Platform: UNKNOWN
Classifier: Development Status :: 3 - Alpha
Classifier: Environment :: Web Environment
Classifier: Framework :: Plone :: 4.3
Classifier: Framework :: Plone
Classifier: Intended Audience :: System Administrators
Classifier: License :: OSI Approved :: GNU General Public License v2 (GPLv2)
Classifier: Operating System :: OS Independent
Classifier: Programming Language :: Python :: 2.7
Classifier: Programming Language :: Python
Classifier: Topic :: Software Development :: Libraries :: Python Modules
Requires-Dist: lxml
Requires-Dist: plone.api
Requires-Dist: plone.app.layout
Requires-Dist: plone.app.registry
Requires-Dist: plone.autoform
Requires-Dist: plone.behavior
Requires-Dist: plone.dexterity
Requires-Dist: plone.supermodel
Requires-Dist: Products.CMFCore
Requires-Dist: Products.CMFPlone (>=4.3)
Requires-Dist: Products.GenericSetup
Requires-Dist: requests
Requires-Dist: setuptools
Requires-Dist: zope.i18nmessageid
Requires-Dist: zope.interface
Requires-Dist: zope.schema
Provides-Extra: test
Requires-Dist: AccessControl; extra == 'test'
Requires-Dist: plone.app.contenttypes; extra == 'test'
Requires-Dist: plone.app.robotframework; extra == 'test'
Requires-Dist: plone.app.testing[robot]; extra == 'test'
Requires-Dist: plone.browserlayer; extra == 'test'
Requires-Dist: plone.registry; extra == 'test'
Requires-Dist: plone.testing; extra == 'test'
Requires-Dist: robotsuite; extra == 'test'
Requires-Dist: zope.component; extra == 'test'
